dbis_relational_calculus-1.0.12.post2.dist-info/licenses/LICENSE
relational_calculus/__init__.py
relational_calculus/domain_calculus/DomainCalculus.py
relational_calculus/domain_calculus/Result.py
relational_calculus/domain_calculus/Variable.py
relational_calculus/domain_calculus/__init__.py
relational_calculus/domain_calculus/formulas/Formula.py
relational_calculus/domain_calculus/formulas/Tuple.py
relational_calculus/domain_calculus/formulas/atoms/Equals.py
relational_calculus/domain_calculus/formulas/atoms/GreaterEquals.py
relational_calculus/domain_calculus/formulas/atoms/GreaterThan.py
relational_calculus/domain_calculus/formulas/atoms/LessEquals.py
relational_calculus/domain_calculus/formulas/atoms/LessThan.py
relational_calculus/domain_calculus/formulas/atoms/__init__.py
relational_calculus/domain_calculus/formulas/connectives/And.py
relational_calculus/domain_calculus/formulas/connectives/Not.py
relational_calculus/domain_calculus/formulas/connectives/Or.py
relational_calculus/domain_calculus/formulas/connectives/__init__.py
relational_calculus/domain_calculus/formulas/quantifiers/Exists.py
relational_calculus/domain_calculus/formulas/quantifiers/Forall.py
relational_calculus/domain_calculus/formulas/quantifiers/__init__.py
relational_calculus/tuple_calculus/Result.py
relational_calculus/tuple_calculus/TupleCalculus.py
relational_calculus/tuple_calculus/__init__.py
relational_calculus/tuple_calculus/formulas/Formula.py
relational_calculus/tuple_calculus/formulas/Variable.py
relational_calculus/tuple_calculus/formulas/atoms/Equals.py
relational_calculus/tuple_calculus/formulas/atoms/GreaterEquals.py
relational_calculus/tuple_calculus/formulas/atoms/GreaterThan.py
relational_calculus/tuple_calculus/formulas/atoms/LessEquals.py
relational_calculus/tuple_calculus/formulas/atoms/LessThan.py
relational_calculus/tuple_calculus/formulas/atoms/__init__.py
relational_calculus/tuple_calculus/formulas/connectives/And.py
relational_calculus/tuple_calculus/formulas/connectives/Not.py
dbis_relational_calculus-1.0.12.post2.dist-info/METADATA
dbis_relational_calculus-1.0.12.post2.dist-info/WHEEL
dbis_relational_calculus-1.0.12.post2.dist-info/top_level.txt
dbis_relational_calculus-1.0.12.post2.dist-info/RECORD
